{
  "url": "https://www.gsb.stanford.edu/insights/utility-player-paul-oyer-explains-how-economics-can-make-sports-more-fun",
  "requestedUrl": "https://www.gsb.stanford.edu/insights/utility-player-paul-oyer-explains-how-economics-can-make-sports-more-fun",
  "timestamp": 1661609213372,
  "ranks": {
    "hundos": 3,
    "performance": 1,
    "accessibility": 2,
    "cumulative": 3
  },
  "lighthouse": {
    "version": "9.6.6",
    "performance": 0.37,
    "accessibility": 1,
    "bestPractices": 0.92,
    "seo": 0.86,
    "total": 315
  },
  "firstContentfulPaint": 3035.009000000001,
  "firstMeaningfulPaint": 3035.009000000001,
  "speedIndex": 7711.41826631581,
  "largestContentfulPaint": 3755.2810000000018,
  "totalBlockingTime": 2702.5,
  "cumulativeLayoutShift": 0.00026855468749999997,
  "timeToInteractive": 18431.500000000004,
  "maxPotentialFirstInputDelay": 1249,
  "timeToFirstByte": 31.948000000000008,
  "weight": {
    "summary": "219 requests • 1,979 KiB",
    "total": 2026890,
    "image": 246346,
    "imageCount": 40,
    "script": 1405874,
    "scriptCount": 43,
    "document": 104040,
    "font": 125681,
    "fontCount": 6,
    "stylesheet": 133528,
    "stylesheetCount": 96,
    "thirdParty": 1373051,
    "thirdPartyCount": 99
  },
  "run": {
    "number": 1,
    "total": 3
  },
  "sidequests": {
    "-weight.total": 6,
    "+weight.total": 8,
    "-weight.document": 3,
    "+weight.document": 11,
    "-weight.script": 6,
    "+weight.script": 8,
    "-weight.image": 10,
    "+weight.image": 4,
    "-weight.font": 7,
    "+weight.font": 7,
    "+weight.fontCount": 4,
    "-timeToFirstByte": 7,
    "-totalBlockingTime": 1,
    "-largestContentfulPaint": 1
  },
  "axe": {
    "passes": 1221,
    "violations": 21
  }
}